{
	"solution": {
		"name" : "xyo-data-structures",
		"type" : "xyo-cpp",
		"projects": [
			{
				"name" : "xyo-data-structures",
				"make" : "dll-or-lib",
				"SPDX-License-Identifier": "MIT",
				"sourcePath" : "XYO/DataStructures",
				"dependency" : [
					"xyo-managed-memory"
				]
			},
			{
				"name": "xyo-data-structures.static",
				"make": "lib",
				"category": "make",
				"SPDX-License-Identifier": "MIT",
				"sourcePath" : "XYO/DataStructures",
				"dependency" : [
					"xyo-managed-memory.static"
				],
				"dependencyDefines" : [
					"XYO_DATASTRUCTURES_LIBRARY"
				],
				"linkVersion": "xyo-data-structures",
				"crt": "static"
			},
			{
				"name" : "test.01",
				"make" : "exe",
				"category" : "test",
				"SPDX-License-Identifier": "Unlicense",
				"dependency" : [
					"xyo-data-structures"
				]
			}
		]
	}
}
